gkbus/__init__.py
gkbus/utils.py
gkbus/hardware/__init__.py
gkbus/hardware/can_hardware.py
gkbus/hardware/hardware_abc.py
gkbus/hardware/kline_hardware.py
gkbus/protocol/__init__.py
gkbus/protocol/protocol_abc.py
gkbus/protocol/ccp/__init__.py
gkbus/protocol/ccp/ccp_command.py
gkbus/protocol/ccp/ccp_protocol.py
gkbus/protocol/ccp/ccp_response.py
gkbus/protocol/ccp/commands.py
gkbus/protocol/ccp/enums.py
gkbus/protocol/ccp/types.py
gkbus/protocol/kwp2000/__init__.py
gkbus/protocol/kwp2000/commands.py
gkbus/protocol/kwp2000/enums.py
gkbus/protocol/kwp2000/kwp2000_command.py
gkbus/protocol/kwp2000/kwp2000_negative_status.py
gkbus/protocol/kwp2000/kwp2000_protocol.py
gkbus/protocol/kwp2000/kwp2000_response.py
gkbus/transport/__init__.py
gkbus/transport/ccp_over_can_transport.py
gkbus/transport/kwp2000_over_can_transport.py
gkbus/transport/kwp2000_over_kline_transport.py
gkbus/transport/transport_abc.py
gkbus-0.4.85.dist-info/licenses/LICENSE
gkbus-0.4.85.dist-info/WHEEL
gkbus-0.4.85.dist-info/METADATA
gkbus-0.4.85.dist-info/RECORD
