Metadata-Version: 2.4
Name: gkbus
Version: 0.4.85
Summary: GKBus: High level automotive protocol library
Author-email: Dante <dante383@protonmail.com>
License-File: LICENSE
Requires-Dist: scapy==2.5.0
Requires-Dist: pyserial==3.5
Requires-Dist: ruff == 0.11.4 ; extra == "lint"
Requires-Dist: mypy == 1.15.0 ; extra == "lint"
Provides-Extra: lint
